desalination_and_brine_treatment/__init__.py
desalination_and_brine_treatment/comparison.py
desalination_and_brine_treatment/constants.py
desalination_and_brine_treatment/density_calc.py
desalination_and_brine_treatment/economic_f.py
desalination_and_brine_treatment/ed_unit_f.py
desalination_and_brine_treatment/edbm_unit_f.py
desalination_and_brine_treatment/efc_unit_f.py
desalination_and_brine_treatment/example_1.py
desalination_and_brine_treatment/example_2.py
desalination_and_brine_treatment/main.py
desalination_and_brine_treatment/med_unit_f.py
desalination_and_brine_treatment/mfpfr_unit_f.py
desalination_and_brine_treatment/nanofiltration_unit_f.py
desalination_and_brine_treatment/project_directory.py
desalination_and_brine_treatment/ro_unit.py
desalination_and_brine_treatment/ro_unit_f.py
desalination_and_brine_treatment/scaleup.py
desalination_and_brine_treatment/thermal_cryst_f.py
example/__init__.py
example/comparison.py
example/constants.py
example/density_calc.py
example/economic_f.py
example/ed_unit_f.py
example/edbm_unit_f.py
example/efc_unit_f.py
example/example_1.py
example/example_2.py
example/main.py
example/med_unit_f.py
example/mfpfr_unit_f.py
example/nanofiltration_unit_f.py
example/project_directory.py
example/ro_unit.py
example/ro_unit_f.py
example/scaleup.py
example/thermal_cryst_f.py
tests/__init__.py
tests/constants.py
tests/density_calc.py
tests/economic_f.py
tests/economic_unittest.py
tests/ed_unit_f.py
tests/ed_unittest.py
tests/edbm_unit_f.py
tests/edbm_unittest.py
tests/med_unit_f.py
tests/med_unittest.py
tests/mfpfr_unit_f.py
tests/mfpfr_unittest.py
tests/nanofiltration_unit_f.py
tests/nanofiltration_unittest.py
tests/scaleup.py
tests/thermal_cryst_f.py
tests/thermal_cryst_unittest.py
desalination_and_brine_treatment-0.1.dist-info/LICENSE
desalination_and_brine_treatment-0.1.dist-info/METADATA
desalination_and_brine_treatment-0.1.dist-info/WHEEL
desalination_and_brine_treatment-0.1.dist-info/top_level.txt
desalination_and_brine_treatment-0.1.dist-info/RECORD
